[
    {"label":"C2", "btnType":"l", "sound":"%.36"},
    {"btnType":"b","sound":"%.37"},
    {"btnType":"m", "sound":"%.38"},
    {"btnType":"b","sound":"%.39"},
    {"btnType":"r", "sound":"%.40"},
    {"btnType":"l", "sound":"%.41"},
    {"btnType":"b","sound":"%.42"},
    {"btnType":"m", "sound":"%.43"},
    {"btnType":"b","sound":"%.44"},
    {"btnType":"m", "sound":"%.45"},
    {"btnType":"b","sound":"%.46"},
    {"btnType":"r", "sound":"%.47"},

    {"label":"C3", "btnType":"l", "sound":"%.48"},
    {"btnType":"b","sound":"%.49"},
    {"btnType":"m", "sound":"%.50"},
    {"btnType":"b","sound":"%.51"},
    {"btnType":"r", "sound":"%.52"},
    {"btnType":"l", "sound":"%.53"},
    {"btnType":"b","sound":"%.54"},
    {"btnType":"m", "sound":"%.55"},
    {"btnType":"b","sound":"%.56"},
    {"btnType":"m", "sound":"%.57"},
    {"btnType":"b","sound":"%.58"},
    {"btnType":"r", "sound":"%.59"},

    {"label":"C4", "btnType":"l", "sound":"%.60"},
    {"btnType":"b","sound":"%.61"},
    {"btnType":"m", "sound":"%.62"},
    {"btnType":"b","sound":"%.63"},
    {"btnType":"r", "sound":"%.64"},
    {"btnType":"l", "sound":"%.65"},
    {"btnType":"b","sound":"%.66"},
    {"btnType":"m", "sound":"%.67"},
    {"btnType":"b","sound":"%.68"},
    {"btnType":"m", "sound":"%.69"},
    {"btnType":"b","sound":"%.70"},
    {"btnType":"r", "sound":"%.71"},

    {"label":"C5", "btnType":"l", "sound":"%.72"},
    {"btnType":"b","sound":"%.73"},
    {"btnType":"m", "sound":"%.74"},
    {"btnType":"b","sound":"%.75"},
    {"btnType":"r", "sound":"%.76"},
    {"btnType":"l", "sound":"%.77"},
    {"btnType":"b","sound":"%.78"},
    {"btnType":"m", "sound":"%.79"},
    {"btnType":"b","sound":"%.80"},
    {"btnType":"m", "sound":"%.81"},
    {"btnType":"b","sound":"%.82"},
    {"btnType":"r", "sound":"%.83"},

    {"label":"C6", "btnType":"l", "sound":"%.84"},
    {"btnType":"b","sound":"%.85"},
    {"btnType":"m", "sound":"%.86"},
    {"btnType":"b","sound":"%.87"},
    {"btnType":"r", "sound":"%.88"},
    {"btnType":"l", "sound":"%.89"},
    {"btnType":"b","sound":"%.90"},
    {"btnType":"m", "sound":"%.91"},
    {"btnType":"b","sound":"%.92"},
    {"btnType":"m", "sound":"%.93"},
    {"btnType":"b","sound":"%.94"},
    {"btnType":"r", "sound":"%.95"}
]